crams_collection/__init__.py
crams_collection/admin.py
crams_collection/apps.py
crams_collection/asgi.py
crams_collection/constants.py
crams_collection/crams_api_urls.py
crams_collection/models.py
crams_collection/permissions.py
crams_collection/public_urls.py
crams_collection/settings.py
crams_collection/test_settings.py
crams_collection/test_utils.py
crams_collection/urls.py
crams_collection/wsgi.py
crams_collection/config/__init__.py
crams_collection/config/aspect_config.py
crams_collection/config/collection_config.py
crams_collection/constants/__init__.py
crams_collection/constants/api.py
crams_collection/log/__init__.py
crams_collection/log/project_contact_log.py
crams_collection/log/project_log.py
crams_collection/migrations/0001_initial.py
crams_collection/migrations/0002_project_crams_id.py
crams_collection/migrations/0003_init_lookups.py
crams_collection/migrations/0004_projectlog.py
crams_collection/migrations/__init__.py
crams_collection/serializers/__init__.py
crams_collection/serializers/base_project_serializer.py
crams_collection/serializers/contact_project_list.py
crams_collection/serializers/domain_serializers.py
crams_collection/serializers/grant_serializers.py
crams_collection/serializers/project_contact_serializer.py
crams_collection/serializers/project_id_serializer.py
crams_collection/serializers/project_serializer.py
crams_collection/serializers/provision_details.py
crams_collection/serializers/publication_serializers.py
crams_collection/serializers/question_serializers.py
crams_collection/sqls/initial_collection.sql
crams_collection/templates/sample/project-invite.html
crams_collection/templates/sample/project-member-approval.html
crams_collection/templates/sample/project-member-invite-cancelled.html
crams_collection/templates/sample/project-member-invite-decline.html
crams_collection/templates/sample/project-member-reject.html
crams_collection/templates/sample/project-member-request-cancelled.html
crams_collection-1.0.0.5.dist-info/METADATA
crams_collection-1.0.0.5.dist-info/WHEEL
crams_collection-1.0.0.5.dist-info/top_level.txt
crams_collection-1.0.0.5.dist-info/RECORD
